flasksaml/__init__.py
flasksaml/blueprint.py
flasksaml/helper.py
flasksaml/index.py
flasksaml-0.2.0.dist-info/LICENSE
flasksaml-0.2.0.dist-info/METADATA
flasksaml-0.2.0.dist-info/WHEEL
flasksaml-0.2.0.dist-info/top_level.txt
flasksaml-0.2.0.dist-info/RECORD
