Metadata-Version: 2.1
Name: flasksaml
Version: 0.2.0
Summary: A Flask wrapper that implements SAML Service Provider functionalities
Home-page: https://github.com/ninja-van/flasksaml.git
Author: Teddy Hartanto
Author-email: teddyhartanto96@gmail.com
License: MIT
Keywords: saml saml2 flask python3
Platform: UNKNOWN
Classifier: Development Status :: 3 - Alpha
Classifier: Intended Audience :: Developers
Classifier: Operating System :: OS Independent
Classifier: Programming Language :: Python :: 3.6
Classifier: Programming Language :: Python :: 3.7
Classifier: Programming Language :: Python :: 3.8
Classifier: Programming Language :: Python :: 3.9
Requires-Python: >=3.6
Requires-Dist: Flask (>=1.0.2)
Requires-Dist: python3-saml (>=1.10.1)
